wptrfull.v
module wptr_full #(parameter ADDRSIZE = 4

)(
    output reg wfull,
    output [ADDRSIZE-1:0] waddr,
    output reg [ADDRSIZE:0] wptr,
    input [ADDRSIZE:0] w2_rptr,
    input winc,
    input wclk,
    input wrst_n
);

    reg [ADDRSIZE:0] wbin;

    wire [ADDRSIZE:0] wgraynext, wbinnext;

    always @(posedge wclk or negedge wrst_n) begin
        if(!wrst_n) {wbin,wptr} <= 0;
        else {wbin,wptr} <= {wbinnext,wgraynext};
    end

    //Binary address for memory

    assign waddr = wbin[ADDRSIZE-1:0];

    // Next Binary: update if not full and winc = 1
    assign wbinnext = wbin + (winc & ~wfull);

    //Binary to Gray 

    assign wgraynext = (wbinnext >> 1) ^ wbinnext;


    wire wfull_val = (wgraynext == {~w2_rptr[ADDRSIZE:ADDRSIZE-1],w2_rptr[ADDRSIZE-2:0]});

    always @(posedge wclk or negedge wrst_n) begin
        if(!wrst_n) wfull <= 1'b0;
        else wfull <= wfull_val;
    end 



    
endmodule

rptrf_empty.v
module rptr_empty #(
    parameter ADDRSIZE = 4
    
)(
    output reg rempty, // FIFO Empty flag generation 
    output [ADDRSIZE-1:0] raddr, //binary addr -> goes to the memory to get the read data address
    output reg [ADDRSIZE:0] rptr, // gray code of read pointer goes to write empty module to calculate the empty condition 
    input [ADDRSIZE:0] r2_wptr, // synchronized write pointer from the sync_w2r module 
    input rinc, // read increment
    input rclk,
    input rrst_n 
);

    reg [ADDRSIZE:0] rbin; //binary counter

    wire [ADDRSIZE:0] rgraynext, rbinnext; //next values

    always @(posedge rclk or negedge rrst_n) begin
        if(!rrst_n) {rbin,rptr} <= 0;
        else {rbin, rptr} <= {rbinnext,rgraynext}; //update both of them 
    end

    //Binary address for memory is jus the lower addrsize bits
    assign raddr = rbin[ADDRSIZE-1:0];

    //increment only if fifo is not empty and read increment is 1
    assign rbinnext = rbin + (rinc & ~rempty);

    // Binary to Gray Conversion 
    assign rgraynext = (rbinnext >> 1)^rbinnext;


    // empty condition generation

    wire rempty_val = (rgraynext == r2_wptr);

    always @(posedge rclk or negedge rrst_n) begin
        if(!rrst_n) rempty <= 1'b1;
        else rempty <= rempty_val;
    end



endmodule

fifomem.v


//Dual Port Ram -- Fifo Mem 
module fifomem #(
    parameter DATASIZE = 8,
    parameter ADDRSIZE = 4
)(
    output [DATASIZE-1:0] rdata,
    input [DATASIZE-1:0] wdata,
    input [ADDRSIZE-1:0] waddr, raddr,
    input wclken, // Write enable same as win
    input wfull, 
    input wclk
);

    localparam DEPTH = 1 << ADDRSIZE; // Depth == 2^addrsize, here 2^4 -- 16. 16 locations (0->15).
 
    reg [DATASIZE-1:0] mem[0:DEPTH-1];

    //Asynchronous Read in this fifo design read - data appears immediately when raddr changes
    assign rdata = mem[raddr];

    //Synchronous write -- only when fifo is not full 

    always @(posedge wclk) begin
        if(wclken && !wfull)
            mem[waddr] <= wdata;
    end



endmodule

syncw2r.v
module sync_w2r #(parameter ADDRSIZE = 4)
(
    output reg [ADDRSIZE:0] rd2_wptr, 
    input [ADDRSIZE:0] wptr,
    input rclk,
    input rrst_n 
);
    reg [ADDRSIZE:0] rd1_wptr;

    always @(posedge rclk or negedge rrst_n) begin
        if (!rrst_n) {rd2_wptr,rd1_wptr} <= 0;
        else {rd2_wptr, rd1_wptr} <= {rd1_wptr, wptr};        
    end


endmodule

syncr2w.v
module sync_r2w #(parameter ADDRSIZE = 4)
(
    output reg [ADDRSIZE:0] w2_rptr, 
    input [ADDRSIZE:0] rptr,
    input wclk,
    input wrst_n 
);
    reg [ADDRSIZE:0] w1_rptr;

    always @(posedge wclk or negedge wrst_n) begin
        if (!wrst_n) {w2_rptr,w1_rptr} <= 0;
        else {w2_rptr, w1_rptr} <= {w1_rptr, rptr};        
    end


endmodule

fifo.v
module fifo #(
    parameter DSIZE = 8, 
    parameter ASIZE = 4
)(
    output [DSIZE-1:0] rdata,
    output wfull,
    output rempty,
    input [DSIZE-1:0] wdata,
    input winc, wclk, wrst_n,
    input rinc, rclk, rrst_n
);

    wire [ASIZE-1:0] waddr, raddr; // addresses to access the fifo memory
    wire [ASIZE:0] wptr, rptr, w2_rptr, r2_wptr; //pointers for address generation and full and empty condition generation


    //Synchronize the read pointer to the write clock domain

    sync_r2w #(ASIZE) sync_r2w(
        .w2_rptr(w2_rptr),.rptr(rptr),
        .wclk(wclk),.wrst_n(wrst_n)
    );

    //Synchronize the write pointer to the read clock domain


    sync_w2r #(ASIZE) sync_w2r (
    .rd2_wptr(r2_wptr), .wptr(wptr),
    .rclk(rclk), .rrst_n(rrst_n));

    // instantiate dual port ram 
    fifomem #(DSIZE,ASIZE) fifomem(
        .rdata(rdata), .wdata(wdata),
        .waddr(waddr), .raddr(raddr),
        .wclken(winc), .wfull(wfull),
        .wclk(wclk)
    );

    // Empty condition generation and read pointer logic

    rptr_empty #(ASIZE) rptr_empty (
        .rempty(rempty), .raddr(raddr),
        .rptr(rptr), .r2_wptr(r2_wptr),
        .rinc(rinc), .rclk(rclk), .rrst_n(rrst_n)
    );


    // Full condition generation and Write Pointer Logic 

    wptr_full #(ASIZE) wptr_full(
        .wfull(wfull), .waddr(waddr),
        .wptr(wptr), .w2_rptr(w2_rptr),
        .winc(winc), .wclk(wclk), .wrst_n(wrst_n)
    );



endmodule

fifo_tb.v
`timescale 1ns/1ps


module tb_fifo;

parameter DSIZE = 8;
parameter ASIZE = 4;  //depth = 2^4 = 16 locations


//-- Input Test Signals -- //
reg [7:0] wdata;
reg winc, wclk, wrst_n;
reg rinc, rclk, rrst_n;


//-- Output Test Signals -- //
wire [7:0] rdata;
wire wfull, rempty;


integer i;

// Instantiate the design for testing

fifo #(DSIZE,ASIZE) dut(
    .rdata(rdata), .wfull(wfull), .rempty(rempty),
    .wdata(wdata), .winc(winc), .wclk(wclk), .wrst_n(wrst_n),
    .rinc(rinc), .rclk(rclk), .rrst_n(rrst_n)
);

// Write Clk -- 100 MHz
initial wclk = 0; 
always #5 wclk = ~wclk;

//Read Clk less than write Clk -- 67Mhz
initial rclk = 0; 
always #7.5 rclk = ~rclk;


// Test Cases 


initial begin
    $dumpfile("test.vcd");
    $dumpvars(0,tb_fifo);


    $display("--- RESET ---");
    winc=0; rinc=0; wdata=0;
    wrst_n=0; rrst_n=0;
    repeat(4) @(posedge wclk);          //After a write or read, the pointer has to cross the clock domain through a 2 flip-flop synchronizer. That takes at least 2 cycles of the destination clock, wait for 4 cycles to  safely check the flags
    wrst_n=1; rrst_n=1;
    repeat(2) @(posedge rclk);
    $display("rempty=%b wfull=%b (expect 1 0)", rempty, wfull);

    // check if empty flag goes down when data is written

    $display("\n--- WRITE 4 WORDS ---");
    for(i=1;i<=4;i=i+1)begin 

        @(negedge wclk);
        wdata = i*10;
        winc = 1;
        @(negedge wclk);
        winc = 0;
        $display("Wrote 0x%02h", wdata);

    end

    repeat(4) @(posedge rclk);
    $display("rempty = %b",rempty);

    // READ those 4 data written

    $display("Read 4 Words");
    for (i = 0; i < 4; i = i+1) begin
      @(negedge rclk);
      $display("read  0x%02h", rdata);  // capture before rinc because logic for output read data is combinational when raddr updates read data is fetched out
      rinc = 1;
      @(negedge rclk);
      rinc = 0;

    end

    repeat(4) @(posedge rclk);
    $display("rempty=%b ", rempty); // should come as 1 because all the data is read from the memory;
    
    // write full and check if full flag gets asserted 


    $display("\n--- FILL TO FULL ---");
    for (i = 0; i < 16; i = i+1) begin
      @(negedge wclk);
      wdata = i;
      winc  = 1;
      @(negedge wclk);
      winc  = 0;
    end
    repeat(4) @(posedge wclk);
    $display("wfull=%b (expect 1)", wfull);

    // Try write when full (overflow check)
    $display("\n--- WRITE WHEN FULL ---");
    @(negedge wclk);
    wdata = 8'hFF; winc = 1;
    @(negedge wclk);
    winc = 0;
    repeat(2) @(posedge wclk);
    $display("wfull=%b", wfull); // expect 1, no overflow.
 
    // read completely (16 reads)
    $display("\n--- DRAIN TO EMPTY ---");
    for (i = 0; i < 16; i = i+1) begin
      @(negedge rclk);
      rinc = 1;
      @(negedge rclk);
      rinc = 0;
    end
    repeat(4) @(posedge rclk);
    $display("rempty=%b", rempty); //(expect 1)
 
    
    // Try read when empty (underflow check)
    
    $display("\n--- READ WHEN EMPTY ---");
    @(negedge rclk);
    rinc = 1;
    @(negedge rclk);
    rinc = 0;
    repeat(2) @(posedge rclk);
    $display("rempty=%b", rempty); //(expect 1, no underflow)
 
    $display("\n--- DONE ---");
    $finish;
  end
 
endmodule

test.vcd
$date
	Thu Jun 25 13:58:59 2026
$end
$version
	Icarus Verilog
$end
$timescale
	1ps
$end
$scope module tb_fifo $end
$var wire 1 ! wfull $end
$var wire 1 " rempty $end
$var wire 8 # rdata [7:0] $end
$var parameter 32 $ ASIZE $end
$var parameter 32 % DSIZE $end
$var reg 1 & rclk $end
$var reg 1 ' rinc $end
$var reg 1 ( rrst_n $end
$var reg 1 ) wclk $end
$var reg 8 * wdata [7:0] $end
$var reg 1 + winc $end
$var reg 1 , wrst_n $end
$var integer 32 - i [31:0] $end
$scope module dut $end
$var wire 1 & rclk $end
$var wire 1 ' rinc $end
$var wire 1 ( rrst_n $end
$var wire 1 ) wclk $end
$var wire 8 . wdata [7:0] $end
$var wire 1 + winc $end
$var wire 1 , wrst_n $end
$var wire 5 / wptr [4:0] $end
$var wire 1 ! wfull $end
$var wire 4 0 waddr [3:0] $end
$var wire 5 1 w2_rptr [4:0] $end
$var wire 5 2 rptr [4:0] $end
$var wire 1 " rempty $end
$var wire 8 3 rdata [7:0] $end
$var wire 4 4 raddr [3:0] $end
$var wire 5 5 r2_wptr [4:0] $end
$var parameter 32 6 ASIZE $end
$var parameter 32 7 DSIZE $end
$scope module fifomem $end
$var wire 8 8 rdata [7:0] $end
$var wire 1 ) wclk $end
$var wire 1 + wclken $end
$var wire 8 9 wdata [7:0] $end
$var wire 1 ! wfull $end
$var wire 4 : waddr [3:0] $end
$var wire 4 ; raddr [3:0] $end
$var parameter 32 < ADDRSIZE $end
$var parameter 32 = DATASIZE $end
$var parameter 36 > DEPTH $end
$upscope $end
$scope module rptr_empty $end
$var wire 1 & rclk $end
$var wire 5 ? rgraynext [4:0] $end
$var wire 1 ' rinc $end
$var wire 1 ( rrst_n $end
$var wire 1 @ rempty_val $end
$var wire 5 A rbinnext [4:0] $end
$var wire 4 B raddr [3:0] $end
$var wire 5 C r2_wptr [4:0] $end
$var parameter 32 D ADDRSIZE $end
$var reg 5 E rbin [4:0] $end
$var reg 1 " rempty $end
$var reg 5 F rptr [4:0] $end
$upscope $end
$scope module sync_r2w $end
$var wire 5 G rptr [4:0] $end
$var wire 1 ) wclk $end
$var wire 1 , wrst_n $end
$var parameter 32 H ADDRSIZE $end
$var reg 5 I w1_rptr [4:0] $end
$var reg 5 J w2_rptr [4:0] $end
$upscope $end
$scope module sync_w2r $end
$var wire 1 & rclk $end
$var wire 1 ( rrst_n $end
$var wire 5 K wptr [4:0] $end
$var parameter 32 L ADDRSIZE $end
$var reg 5 M rd1_wptr [4:0] $end
$var reg 5 N rd2_wptr [4:0] $end
$upscope $end
$scope module wptr_full $end
$var wire 5 O w2_rptr [4:0] $end
$var wire 1 ) wclk $end
$var wire 5 P wgraynext [4:0] $end
$var wire 1 + winc $end
$var wire 1 , wrst_n $end
$var wire 1 Q wfull_val $end
$var wire 5 R wbinnext [4:0] $end
$var wire 4 S waddr [3:0] $end
$var parameter 32 T ADDRSIZE $end
$var reg 5 U wbin [4:0] $end
$var reg 1 ! wfull $end
$var reg 5 V wptr [4:0] $end
$upscope $end
$upscope $end
$upscope $end
$enddefinitions $end
$comment Show the parameter values. $end
$dumpall
b100 T
b100 L
b100 H
b100 D
b10000 >
b1000 =
b100 <
b1000 7
b100 6
b1000 %
b100 $
$end
#0
$dumpvars
b0 V
b0 U
b0 S
b0 R
0Q
b0 P
b0 O
b0 N
b0 M
b0 K
b0 J
b0 I
b0 G
b0 F
b0 E
b0 C
b0 B
b0 A
1@
b0 ?
b0 ;
b0 :
b0 9
bx 8
b0 5
b0 4
bx 3
b0 2
b0 1
b0 0
b0 /
b0 .
bx -
0,
0+
b0 *
0)
0(
0'
0&
bx #
1"
0!
$end
#5000
1)
#7500
1&
#10000
0)
#15000
1)
0&
#20000
0)
#22500
1&
#25000
1)
#30000
0)
0&
#35000
1(
1,
1)
#37500
1&
#40000
0)
#45000
1)
0&
#50000
0)
#52500
b1 -
1&
#55000
1)
#60000
b1 P
b1 R
1+
b1010 *
b1010 .
b1010 9
0)
0&
#65000
b1 0
b1 :
b1 S
b11 P
b1010 #
b1010 3
b1010 8
b10 R
b1 U
b1 /
b1 K
b1 V
1)
#67500
b1 M
1&
#70000
b1 P
b1 R
b10 -
0+
0)
#75000
1)
0&
#80000
b11 P
b10 R
1+
b10100 *
b10100 .
b10100 9
0)
#82500
0@
b1 5
b1 C
b1 N
1&
#85000
b10 0
b10 :
b10 S
b10 P
b11 R
b10 U
b11 /
b11 K
b11 V
1)
#90000
b11 P
b10 R
b11 -
0+
0)
0&
#95000
1)
#97500
0"
b11 M
1&
#100000
b10 P
b11 R
1+
b11110 *
b11110 .
b11110 9
0)
#105000
b11 0
b11 :
b11 S
b110 P
b100 R
b11 U
b10 /
b10 K
b10 V
1)
0&
#110000
b10 P
b11 R
b100 -
0+
0)
#112500
b11 5
b11 C
b11 N
b10 M
1&
#115000
1)
#120000
b110 P
b100 R
1+
b101000 *
b101000 .
b101000 9
0)
0&
#125000
b100 0
b100 :
b100 S
b111 P
b101 R
b100 U
b110 /
b110 K
b110 V
1)
#127500
b10 5
b10 C
b10 N
b110 M
1&
#130000
b110 P
b100 R
b101 -
0+
0)
#135000
1)
0&
#140000
0)
#142500
b110 5
b110 C
b110 N
1&
#145000
1)
#150000
0)
0&
#155000
1)
#157500
1&
#160000
0)
#165000
1)
0&
#170000
0)
#172500
1&
#175000
1)
#180000
0)
0&
#185000
1)
#187500
b0 -
1&
#190000
0)
#195000
b1 ?
b1 A
1'
1)
0&
#200000
0)
#202500
b10100 #
b10100 3
b10100 8
b1 4
b1 ;
b1 B
b11 ?
b10 A
b1 E
b1 2
b1 F
b1 G
1&
#205000
b1 I
1)
#210000
b1 ?
b1 A
b1 -
0'
0)
0&
#215000
b1 1
b1 J
b1 O
1)
#217500
1&
#220000
0)
#225000
b11 ?
b10 A
1'
1)
0&
#230000
0)
#232500
b11110 #
b11110 3
b11110 8
b10 4
b10 ;
b10 B
b10 ?
b11 A
b10 E
b11 2
b11 F
b11 G
1&
#235000
b11 I
1)
#240000
b11 ?
b10 A
b10 -
0'
0)
0&
#245000
b11 1
b11 J
b11 O
1)
#247500
1&
#250000
0)
#255000
b10 ?
b11 A
1'
1)
0&
#260000
0)
#262500
1@
b101000 #
b101000 3
b101000 8
b11 4
b11 ;
b11 B
b110 ?
b100 A
b11 E
b10 2
b10 F
b10 G
1&
#265000
b10 I
1)
#270000
0@
b10 ?
b11 A
b11 -
0'
0)
0&
#275000
b10 1
b10 J
b10 O
1)
#277500
1&
#280000
0)
#285000
1@
b110 ?
b100 A
1'
1)
0&
#290000
0)
#292500
bx #
bx 3
bx 8
b100 4
b100 ;
b100 B
1@
b110 ?
b100 A
b100 E
b110 2
b110 F
b110 G
1"
1&
#295000
b110 I
1)
#300000
b100 -
0'
0)
0&
#305000
b110 1
b110 J
b110 O
1)
#307500
1&
#310000
0)
#315000
1)
0&
#320000
0)
#322500
1&
#325000
1)
#330000
0)
0&
#335000
1)
#337500
1&
#340000
0)
#345000
1)
0&
#350000
0)
#352500
b0 -
1&
#355000
1)
#360000
b111 P
b101 R
1+
b0 *
b0 .
b0 9
0)
0&
#365000
b101 0
b101 :
b101 S
b101 P
b0 #
b0 3
b0 8
b110 R
b101 U
b111 /
b111 K
b111 V
1)
#367500
b111 M
1&
#370000
b111 P
b101 R
b1 -
0+
0)
#375000
1)
0&
#380000
b101 P
b110 R
1+
b1 *
b1 .
b1 9
0)
#382500
0@
b111 5
b111 C
b111 N
1&
#385000
b110 0
b110 :
b110 S
b100 P
b111 R
b110 U
b101 /
b101 K
b101 V
1)
#390000
b101 P
b110 R
b10 -
0+
0)
0&
#395000
1)
#397500
0"
b101 M
1&
#400000
b100 P
b111 R
1+
b10 *
b10 .
b10 9
0)
#405000
b111 0
b111 :
b111 S
b1100 P
b1000 R
b111 U
b100 /
b100 K
b100 V
1)
0&
#410000
b100 P
b111 R
b11 -
0+
0)
#412500
b101 5
b101 C
b101 N
b100 M
1&
#415000
1)
#420000
b1100 P
b1000 R
1+
b11 *
b11 .
b11 9
0)
0&
#425000
b1000 0
b1000 :
b1000 S
b1101 P
b1001 R
b1000 U
b1100 /
b1100 K
b1100 V
1)
#427500
b100 5
b100 C
b100 N
b1100 M
1&
#430000
b1100 P
b1000 R
b100 -
0+
0)
#435000
1)
0&
#440000
b1101 P
b1001 R
1+
b100 *
b100 .
b100 9
0)
#442500
b1100 5
b1100 C
b1100 N
1&
#445000
b1001 0
b1001 :
b1001 S
b1111 P
b1010 R
b1001 U
b1101 /
b1101 K
b1101 V
1)
#450000
b1101 P
b1001 R
b101 -
0+
0)
0&
#455000
1)
#457500
b1101 M
1&
#460000
b1111 P
b1010 R
1+
b101 *
b101 .
b101 9
0)
#465000
b1010 0
b1010 :
b1010 S
b1110 P
b1011 R
b1010 U
b1111 /
b1111 K
b1111 V
1)
0&
#470000
b1111 P
b1010 R
b110 -
0+
0)
#472500
b1101 5
b1101 C
b1101 N
b1111 M
1&
#475000
1)
#480000
b1110 P
b1011 R
1+
b110 *
b110 .
b110 9
0)
0&
#485000
b1011 0
b1011 :
b1011 S
b1010 P
b1100 R
b1011 U
b1110 /
b1110 K
b1110 V
1)
#487500
b1111 5
b1111 C
b1111 N
b1110 M
1&
#490000
b1110 P
b1011 R
b111 -
0+
0)
#495000
1)
0&
#500000
b1010 P
b1100 R
1+
b111 *
b111 .
b111 9
0)
#502500
b1110 5
b1110 C
b1110 N
1&
#505000
b1100 0
b1100 :
b1100 S
b1011 P
b1101 R
b1100 U
b1010 /
b1010 K
b1010 V
1)
#510000
b1010 P
b1100 R
b1000 -
0+
0)
0&
#515000
1)
#517500
b1010 M
1&
#520000
b1011 P
b1101 R
1+
b1000 *
b1000 .
b1000 9
0)
#525000
b1101 0
b1101 :
b1101 S
b1001 P
b1110 R
b1101 U
b1011 /
b1011 K
b1011 V
1)
0&
#530000
b1011 P
b1101 R
b1001 -
0+
0)
#532500
b1010 5
b1010 C
b1010 N
b1011 M
1&
#535000
1)
#540000
b1001 P
b1110 R
1+
b1001 *
b1001 .
b1001 9
0)
0&
#545000
b1110 0
b1110 :
b1110 S
b1000 P
b1111 R
b1110 U
b1001 /
b1001 K
b1001 V
1)
#547500
b1011 5
b1011 C
b1011 N
b1001 M
1&
#550000
b1001 P
b1110 R
b1010 -
0+
0)
#555000
1)
0&
#560000
b1000 P
b1111 R
1+
b1010 *
b1010 .
b1010 9
0)
#562500
b1001 5
b1001 C
b1001 N
1&
#565000
b1111 0
b1111 :
b1111 S
b11000 P
b10000 R
b1111 U
b1000 /
b1000 K
b1000 V
1)
#570000
b1000 P
b1111 R
b1011 -
0+
0)
0&
#575000
1)
#577500
b1000 M
1&
#580000
b11000 P
b10000 R
1+
b1011 *
b1011 .
b1011 9
0)
#585000
b0 0
b0 :
b0 S
b11001 P
b10001 R
b10000 U
b11000 /
b11000 K
b11000 V
1)
0&
#590000
b11000 P
b10000 R
b1100 -
0+
0)
#592500
b1000 5
b1000 C
b1000 N
b11000 M
1&
#595000
1)
#600000
b11001 P
b10001 R
1+
b1100 *
b1100 .
b1100 9
0)
0&
#605000
b1 0
b1 :
b1 S
b11011 P
b10010 R
b10001 U
b11001 /
b11001 K
b11001 V
1)
#607500
b11000 5
b11000 C
b11000 N
b11001 M
1&
#610000
b11001 P
b10001 R
b1101 -
0+
0)
#615000
1)
0&
#620000
b11011 P
b10010 R
1+
b1101 *
b1101 .
b1101 9
0)
#622500
b11001 5
b11001 C
b11001 N
1&
#625000
b10 0
b10 :
b10 S
b11010 P
b10011 R
b10010 U
b11011 /
b11011 K
b11011 V
1)
#630000
b11011 P
b10010 R
b1110 -
0+
0)
0&
#635000
1)
#637500
b11011 M
1&
#640000
b11010 P
b10011 R
1+
b1110 *
b1110 .
b1110 9
0)
#645000
1Q
b11 0
b11 :
b11 S
b11110 P
b10100 R
b10011 U
b11010 /
b11010 K
b11010 V
1)
0&
#650000
0Q
b11010 P
b10011 R
b1111 -
0+
0)
#652500
b11011 5
b11011 C
b11011 N
b11010 M
1&
#655000
1)
#660000
1Q
b11110 P
b10100 R
1+
b1111 *
b1111 .
b1111 9
0)
0&
#665000
b100 0
b100 :
b100 S
1Q
b11110 P
1!
b10100 R
b10100 U
b11110 /
b11110 K
b11110 V
1)
#667500
b11010 5
b11010 C
b11010 N
b11110 M
1&
#670000
b10000 -
0+
0)
#675000
1)
0&
#680000
0)
#682500
b11110 5
b11110 C
b11110 N
1&
#685000
1)
#690000
0)
0&
#695000
1)
#697500
1&
#700000
0)
#705000
1)
0&
#710000
1+
b11111111 *
b11111111 .
b11111111 9
0)
#712500
1&
#715000
1)
#720000
0+
0)
0&
#725000
1)
#727500
1&
#730000
0)
#735000
b0 -
1)
0&
#740000
0)
#742500
1&
#745000
1)
#750000
b111 ?
b101 A
1'
0)
0&
#755000
1)
#757500
b1 #
b1 3
b1 8
b101 4
b101 ;
b101 B
b101 ?
b110 A
b101 E
b111 2
b111 F
b111 G
1&
#760000
0)
#765000
b111 I
b111 ?
b101 A
b1 -
0'
1)
0&
#770000
0)
#772500
1&
#775000
0Q
b111 1
b111 J
b111 O
1)
#780000
b101 ?
b110 A
1'
0)
0&
#785000
0!
1)
#787500
b10 #
b10 3
b10 8
b110 4
b110 ;
b110 B
b100 ?
b111 A
b110 E
b101 2
b101 F
b101 G
1&
#790000
0)
#795000
b101 I
b101 ?
b110 A
b10 -
0'
1)
0&
#800000
0)
#802500
1&
#805000
b101 1
b101 J
b101 O
1)
#810000
b100 ?
b111 A
1'
0)
0&
#815000
1)
#817500
b11 #
b11 3
b11 8
b111 4
b111 ;
b111 B
b1100 ?
b1000 A
b111 E
b100 2
b100 F
b100 G
1&
#820000
0)
#825000
b100 I
b100 ?
b111 A
b11 -
0'
1)
0&
#830000
0)
#832500
1&
#835000
b100 1
b100 J
b100 O
1)
#840000
b1100 ?
b1000 A
1'
0)
0&
#845000
1)
#847500
b100 #
b100 3
b100 8
b1000 4
b1000 ;
b1000 B
b1101 ?
b1001 A
b1000 E
b1100 2
b1100 F
b1100 G
1&
#850000
0)
#855000
b1100 I
b1100 ?
b1000 A
b100 -
0'
1)
0&
#860000
0)
#862500
1&
#865000
b1100 1
b1100 J
b1100 O
1)
#870000
b1101 ?
b1001 A
1'
0)
0&
#875000
1)
#877500
b101 #
b101 3
b101 8
b1001 4
b1001 ;
b1001 B
b1111 ?
b1010 A
b1001 E
b1101 2
b1101 F
b1101 G
1&
#880000
0)
#885000
b1101 I
b1101 ?
b1001 A
b101 -
0'
1)
0&
#890000
0)
#892500
1&
#895000
b1101 1
b1101 J
b1101 O
1)
#900000
b1111 ?
b1010 A
1'
0)
0&
#905000
1)
#907500
b110 #
b110 3
b110 8
b1010 4
b1010 ;
b1010 B
b1110 ?
b1011 A
b1010 E
b1111 2
b1111 F
b1111 G
1&
#910000
0)
#915000
b1111 I
b1111 ?
b1010 A
b110 -
0'
1)
0&
#920000
0)
#922500
1&
#925000
b1111 1
b1111 J
b1111 O
1)
#930000
b1110 ?
b1011 A
1'
0)
0&
#935000
1)
#937500
b111 #
b111 3
b111 8
b1011 4
b1011 ;
b1011 B
b1010 ?
b1100 A
b1011 E
b1110 2
b1110 F
b1110 G
1&
#940000
0)
#945000
b1110 I
b1110 ?
b1011 A
b111 -
0'
1)
0&
#950000
0)
#952500
1&
#955000
b1110 1
b1110 J
b1110 O
1)
#960000
b1010 ?
b1100 A
1'
0)
0&
#965000
1)
#967500
b1000 #
b1000 3
b1000 8
b1100 4
b1100 ;
b1100 B
b1011 ?
b1101 A
b1100 E
b1010 2
b1010 F
b1010 G
1&
#970000
0)
#975000
b1010 I
b1010 ?
b1100 A
b1000 -
0'
1)
0&
#980000
0)
#982500
1&
#985000
b1010 1
b1010 J
b1010 O
1)
#990000
b1011 ?
b1101 A
1'
0)
0&
#995000
1)
#997500
b1001 #
b1001 3
b1001 8
b1101 4
b1101 ;
b1101 B
b1001 ?
b1110 A
b1101 E
b1011 2
b1011 F
b1011 G
1&
#1000000
0)
#1005000
b1011 I
b1011 ?
b1101 A
b1001 -
0'
1)
0&
#1010000
0)
#1012500
1&
#1015000
b1011 1
b1011 J
b1011 O
1)
#1020000
b1001 ?
b1110 A
1'
0)
0&
#1025000
1)
#1027500
b1010 #
b1010 3
b1010 8
b1110 4
b1110 ;
b1110 B
b1000 ?
b1111 A
b1110 E
b1001 2
b1001 F
b1001 G
1&
#1030000
0)
#1035000
b1001 I
b1001 ?
b1110 A
b1010 -
0'
1)
0&
#1040000
0)
#1042500
1&
#1045000
b1001 1
b1001 J
b1001 O
1)
#1050000
b1000 ?
b1111 A
1'
0)
0&
#1055000
1)
#1057500
b1011 #
b1011 3
b1011 8
b1111 4
b1111 ;
b1111 B
b11000 ?
b10000 A
b1111 E
b1000 2
b1000 F
b1000 G
1&
#1060000
0)
#1065000
b1000 I
b1000 ?
b1111 A
b1011 -
0'
1)
0&
#1070000
0)
#1072500
1&
#1075000
b1000 1
b1000 J
b1000 O
1)
#1080000
b11000 ?
b10000 A
1'
0)
0&
#1085000
1)
#1087500
b1100 #
b1100 3
b1100 8
b0 4
b0 ;
b0 B
b11001 ?
b10001 A
b10000 E
b11000 2
b11000 F
b11000 G
1&
#1090000
0)
#1095000
b11000 I
b11000 ?
b10000 A
b1100 -
0'
1)
0&
#1100000
0)
#1102500
1&
#1105000
b11000 1
b11000 J
b11000 O
1)
#1110000
b11001 ?
b10001 A
1'
0)
0&
#1115000
1)
#1117500
b1101 #
b1101 3
b1101 8
b1 4
b1 ;
b1 B
b11011 ?
b10010 A
b10001 E
b11001 2
b11001 F
b11001 G
1&
#1120000
0)
#1125000
b11001 I
b11001 ?
b10001 A
b1101 -
0'
1)
0&
#1130000
0)
#1132500
1&
#1135000
b11001 1
b11001 J
b11001 O
1)
#1140000
b11011 ?
b10010 A
1'
0)
0&
#1145000
1)
#1147500
b1110 #
b1110 3
b1110 8
b10 4
b10 ;
b10 B
b11010 ?
b10011 A
b10010 E
b11011 2
b11011 F
b11011 G
1&
#1150000
0)
#1155000
b11011 I
b11011 ?
b10010 A
b1110 -
0'
1)
0&
#1160000
0)
#1162500
1&
#1165000
b11011 1
b11011 J
b11011 O
1)
#1170000
b11010 ?
b10011 A
1'
0)
0&
#1175000
1)
#1177500
1@
b1111 #
b1111 3
b1111 8
b11 4
b11 ;
b11 B
b11110 ?
b10100 A
b10011 E
b11010 2
b11010 F
b11010 G
1&
#1180000
0)
#1185000
b11010 I
0@
b11010 ?
b10011 A
b1111 -
0'
1)
0&
#1190000
0)
#1192500
1&
#1195000
b11010 1
b11010 J
b11010 O
1)
#1200000
1@
b11110 ?
b10100 A
1'
0)
0&
#1205000
1)
#1207500
b0 #
b0 3
b0 8
b100 4
b100 ;
b100 B
1@
b11110 ?
1"
b10100 A
b10100 E
b11110 2
b11110 F
b11110 G
1&
#1210000
0)
#1215000
b11110 I
b10000 -
0'
1)
0&
#1220000
0)
#1222500
1&
#1225000
b11110 1
b11110 J
b11110 O
1)
#1230000
0)
0&
#1235000
1)
#1237500
1&
#1240000
0)
#1245000
1)
0&
#1250000
0)
#1252500
1&
#1255000
1)
#1260000
0)
0&
#1265000
1)
#1267500
1&
#1270000
0)
#1275000
1'
1)
0&
#1280000
0)
#1282500
1&
#1285000
1)
#1290000
0'
0)
0&
